setup.py
ownbot/__init__.py
ownbot/admincommands.py
ownbot/auth.py
ownbot/user.py
ownbot/usermanager.py
ownbot.egg-info/PKG-INFO
ownbot.egg-info/SOURCES.txt
ownbot.egg-info/dependency_links.txt
ownbot.egg-info/requires.txt
ownbot.egg-info/top_level.txt
test/test_admincommands.py
test/test_auth.py
test/test_user.py
test/test_usermanager.py