Metadata-Version: 1.1
Name: ownbot
Version: 0.0.4
Summary: Python module to create private telegram bots.
Home-page: https://github.com/michaelimfeld/ownbot
Author: Michael Imfeld
Author-email: michaelimfeld@crooked.ch
License: MIT
Download-URL: https://github.com/michaelimfeld/ownbot
Keywords: ownbot,python,telegram,bot
Platform: Linux
Platform: Windows
Platform: MAC OS X
Classifier: Programming Language :: Python
Classifier: Programming Language :: Python :: 2.7
Classifier: Programming Language :: Python :: 3
Classifier: Programming Language :: Python :: 3.3
Classifier: Programming Language :: Python :: 3.4
Classifier: Programming Language :: Python :: 3.5
Classifier: Operating System :: OS Independent
Classifier: Intended Audience :: Developers
Classifier: Intended Audience :: Education
Classifier: License :: OSI Approved :: MIT License
Classifier: Natural Language :: English
Classifier: Topic :: Education :: Testing
Classifier: Topic :: Software Development
